hamstercage/__init__.py
hamstercage/__main__.py
hamstercage/hamstercage_exception.py
hamstercage/manifest.py
hamstercage/tests/__init__.py
hamstercage/tests/hamstercage.yaml
hamstercage/tests/repo/tags/all/missing-in-target.txt
hamstercage/tests/repo/tags/all/one.txt
hamstercage/tests/repo/tags/all/two.conf
hamstercage/tests/repo/tags/foo/two.conf
hamstercage/tests/test_hamstercage.py
hamstercage/tests/test_manifest.py
hamstercage/tests/test_utils.py
hamstercage/utils.py
hamstercage-0.2.5.dist-info/LICENSE
hamstercage-0.2.5.dist-info/METADATA
hamstercage-0.2.5.dist-info/WHEEL
hamstercage-0.2.5.dist-info/entry_points.txt
hamstercage-0.2.5.dist-info/RECORD
