Metadata-Version: 2.1
Name: hamstercage
Version: 0.2.5
Summary: Pets not cattle. A straightforward way to manage configuration files.
Home-page: https://hamstercage.io/
License: Apache2.0
Keywords: configuration-management
Author: Stefan Bethke
Author-email: stb@lassitu.de
Requires-Python: >=3.8,<4.0
Classifier: Development Status :: 4 - Beta
Classifier: Environment :: Console
Classifier: Intended Audience :: Developers
Classifier: Intended Audience :: System Administrators
Classifier: License :: OSI Approved :: Apache Software License
Classifier: License :: Other/Proprietary License
Classifier: Operating System :: OS Independent
Classifier: Programming Language :: Python :: 3
Classifier: Programming Language :: Python :: 3.8
Classifier: Programming Language :: Python :: 3.9
Classifier: Programming Language :: Python :: 3.10
Classifier: Programming Language :: Python :: 3.11
Classifier: Programming Language :: Python :: 3.12
Classifier: Topic :: Software Development :: Version Control
Classifier: Topic :: System :: Installation/Setup
Classifier: Topic :: System :: Systems Administration
Classifier: Topic :: Utilities
Requires-Dist: PyYAML (>=6.0.1,<7.0.0)
Requires-Dist: importlib-resources (>=6.0.1,<7.0.0)
Project-URL: Documentation, https://hamstercage.io/documentation/
Project-URL: Repository, https://github.com/hamstercage/hamstercage/
